<?xml version="1.0" encoding="utf-8"?>
<key id="1dc73dd1-1bbf-4a98-bd8e-e44f27896f39" version="1">
  <creationDate>2025-12-09T09:27:03.407107Z</creationDate>
  <activationDate>2025-12-09T09:27:03.40682Z</activationDate>
  <expirationDate>2026-03-09T09:27:03.40682Z</expirationDate>
  <descriptor deserializerType="Microsoft.AspNetCore.DataProtection.AuthenticatedEncryption.ConfigurationModel.AuthenticatedEncryptorDescriptorDeserializer, Microsoft.AspNetCore.DataProtection, Version=8.0.0.0, Culture=neutral, PublicKeyToken=adb9793829ddae60">
    <descriptor>
      <encryption algorithm="AES_256_CBC" />
      <validation algorithm="HMACSHA256" />
      <encryptedSecret decryptorType="Microsoft.AspNetCore.DataProtection.XmlEncryption.NullXmlDecryptor, Microsoft.AspNetCore.DataProtection, Version=8.0.0.0, Culture=neutral, PublicKeyToken=adb9793829ddae60" xmlns="http://schemas.asp.net/2015/03/dataProtection">
        <unencryptedKey xmlns="">
          <!-- This key is not encrypted. -->
          <masterKey p6:requiresEncryption="true" xmlns:p6="http://schemas.asp.net/2015/03/dataProtection">
            <!-- Warning: the key below is in an unencrypted form. -->
            <value>7VlfWATC+H5y8k9l9Q+/zNI8mYhj88XSnG2pEQLwCFL4c5RScSkJdD8CDjPCbFTsxn87eZZ+r7kLqjcWRuMnKA==</value>
          </masterKey>
        </unencryptedKey>
      </encryptedSecret>
    </descriptor>
  </descriptor>
</key>